odoo/addons/maintenance_location/README.rst
odoo/addons/maintenance_location/__init__.py
odoo/addons/maintenance_location/__manifest__.py
odoo/addons/maintenance_location/i18n/es.po
odoo/addons/maintenance_location/i18n/it.po
odoo/addons/maintenance_location/i18n/maintenance_location.pot
odoo/addons/maintenance_location/models/__init__.py
odoo/addons/maintenance_location/models/maintenance_equipment.py
odoo/addons/maintenance_location/models/maintenance_location.py
odoo/addons/maintenance_location/models/maintenance_plan.py
odoo/addons/maintenance_location/models/maintenance_request.py
odoo/addons/maintenance_location/readme/CONTRIBUTORS.md
odoo/addons/maintenance_location/readme/DESCRIPTION.md
odoo/addons/maintenance_location/security/ir.model.access.csv
odoo/addons/maintenance_location/static/description/icon.png
odoo/addons/maintenance_location/static/description/index.html
odoo/addons/maintenance_location/tests/__init__.py
odoo/addons/maintenance_location/tests/test_maintenance_location.py
odoo/addons/maintenance_location/views/maintenance_equipment.xml
odoo/addons/maintenance_location/views/maintenance_location.xml
odoo/addons/maintenance_location/views/maintenance_plan.xml
odoo/addons/maintenance_location/views/maintenance_request.xml
odoo_addon_maintenance_location-17.0.1.0.0.2.dist-info/METADATA
odoo_addon_maintenance_location-17.0.1.0.0.2.dist-info/WHEEL
odoo_addon_maintenance_location-17.0.1.0.0.2.dist-info/top_level.txt
odoo_addon_maintenance_location-17.0.1.0.0.2.dist-info/RECORD
